[
    {
        "id": "bor_getAuthor",
        "value": "bor_getAuthor"
    },
    {
        "id": "bor_getCurrentProposer",
        "value": "bor_getCurrentProposer"
    },
    {
        "id": "bor_getCurrentValidators",
        "value": "bor_getCurrentValidators"
    },
    {
        "id": "bor_getRootHash",
        "value": "bor_getRootHash"
    },
    {
        "id": "bor_getSignersAtHash",
        "value": "bor_getSignersAtHash"
    },
    { "id": "eth_accounts", "value": "eth_accounts" },
    { "id": "eth_blockNumber", "value": "eth_blockNumber" },
    { "id": "eth_call", "value": "eth_call" },
    { "id": "eth_chainID", "value": "eth_chainID" },
    { "id": "eth_estimateGas", "value": "eth_estimateGas" },
    { "id": "eth_feeHistory", "value": "eth_feeHistory" },
    { "id": "eth_gasPrice", "value": "eth_gasPrice" },
    { "id": "eth_getBalance", "value": "eth_getBalance" },
    { "id": "eth_getBlockByHash", "value": "eth_getBlockByHash" },
    { "id": "eth_getBlockByNumber", "value": "eth_getBlockByNumber" },
    {
        "id": "eth_getBlockReceipts",
        "value": "eth_getBlockReceipts"
    },
    {
        "id": "eth_getBlockTransactionCountByHash",
        "value": "eth_getBlockTransactionCountByHash"
    },
    {
        "id": "eth_getBlockTransactionCountByNumber",
        "value": "eth_getBlockTransactionCountByNumber"
    },
    { "id": "eth_getCode", "value": "eth_getCode" },
    { "id": "eth_getFilterChanges", "value": "eth_getFilterChanges" },
    { "id": "eth_getFilterLogs", "value": "eth_getFilterLogs" },
    { "id": "eth_getLogs", "value": "eth_getLogs" },
    { "id": "eth_getProof", "value": "eth_getProof" },
    { "id": "eth_getRootHash", "value": "eth_getRootHash" },
    { "id": "eth_getStorageAt", "value": "eth_getStorageAt" },
    {
        "id": "eth_getTransactionByBlockHashAndIndex",
        "value": "eth_getTransactionByBlockHashAndIndex"
    },
    {
        "id": "eth_getTransactionByBlockNumberAndIndex",
        "value": "eth_getTransactionByBlockNumberAndIndex"
    },
    { "id": "eth_getTransactionByHash", "value": "eth_getTransactionByHash" },
    { "id": "eth_getTransactionCount", "value": "eth_getTransactionCount" },
    { "id": "eth_getTransactionReceipt", "value": "eth_getTransactionReceipt" },
    {
        "id": "eth_getTransactionReceiptsByBlock",
        "value": "eth_getTransactionReceiptsByBlock"
    },
    {
        "id": "eth_getUncleByBlockHashAndIndex",
        "value": "eth_getUncleByBlockHashAndIndex"
    },
    {
        "id": "eth_getUncleByBlockNumberAndIndex",
        "value": "eth_getUncleByBlockNumberAndIndex"
    },
    {
        "id": "eth_getUncleCountByBlockHash",
        "value": "eth_getUncleCountByBlockHash"
    },
    {
        "id": "eth_getUncleCountByBlockNumber",
        "value": "eth_getUncleCountByBlockNumber"
    },
    { "id": "eth_maxPriorityFeePerGas", "value": "eth_maxPriorityFeePerGas" },
    { "id": "eth_newFilter", "value": "eth_newFilter" },
    { "id": "eth_newBlockFilter", "value": "eth_newBlockFilter" },
    {
        "id": "eth_newPendingTransactionFilter",
        "value": "eth_newPendingTransactionFilter"
    },
    { "id": "eth_protocolVersion", "value": "eth_protocolVersion" },
    { "id": "eth_sendRawTransaction", "value": "eth_sendRawTransaction" },
    { "id": "eth_syncing", "value": "eth_syncing" },
    { "id": "eth_uninstallFilter", "value": "eth_uninstallFilter" },
    { "id": "getContractMetadata", "value": "getContractMetadata" },
    { "id": "getFloorPrice", "value": "getFloorPrice" },

    { "id": "getLargestAccounts", "value": "getLargestAccounts" },
    { "id": "getNFTMetadata", "value": "getNFTMetadata" },
    { "id": "getNFTs", "value": "getNFTs" },
    { "id": "getNFTsForCollection", "value": "getNFTsForCollection" },
    { "id": "getOwnersForCollection", "value": "getOwnersForCollection" },
    { "id": "getOwnersForToken", "value": "getOwnersForToken" },
    { "id": "getSpamContracts", "value": "getSpamContracts" },
    { "id": "isSpamContract", "value": "isSpamContract" },
    { "id": "netListening", "value": "netListening" },
    { "id": "netVersion", "value": "netVersion" },
    { "id": "parity_getBlockReceipts", "value": "parity_getBlockReceipts" },
    { "id": "reingestContract", "value": "reingestContract" },
    { "id": "trace_block", "value": "trace_block" },
    { "id": "trace_call", "value": "trace_call" },
    { "id": "trace_rawTransaction", "value": "trace_rawTransaction" },
    {
        "id": "trace_replayBlockTransactions",
        "value": "trace_replayBlockTransactions"
    },
    { "id": "trace_replayTransaction", "value": "trace_replayTransaction" },
    { "id": "trace_transaction", "value": "trace_transaction" },
    { "id": "web3_clientVersion", "value": "web3_clientVersion" },
    { "id": "web3_sha3", "value": "web3_sha3" }
]
